sixfeetup.customfolderalert-1.3-py2.7-nspkg.pth
sixfeetup/customfolderalert/__init__.py
sixfeetup/customfolderalert/configure.zcml
sixfeetup/customfolderalert/skins.zcml
sixfeetup/customfolderalert/version.txt
sixfeetup/customfolderalert/Extensions/Install.py
sixfeetup/customfolderalert/browser/__init__.py
sixfeetup/customfolderalert/browser/alertview.py
sixfeetup/customfolderalert/browser/configure.zcml
sixfeetup/customfolderalert/profiles/default/jsregistry.xml
sixfeetup/customfolderalert/profiles/default/sixfeetup.customfolderalert_default.txt
sixfeetup/customfolderalert/profiles/default/skins.xml
sixfeetup/customfolderalert/profiles/uninstall/jsregistry.xml
sixfeetup/customfolderalert/profiles/uninstall/skins.xml
sixfeetup/customfolderalert/skins/sixfeetup_customfolderalert/evilalert.js.dtml
sixfeetup.customfolderalert-1.3.dist-info/DESCRIPTION.rst
sixfeetup.customfolderalert-1.3.dist-info/METADATA
sixfeetup.customfolderalert-1.3.dist-info/RECORD
sixfeetup.customfolderalert-1.3.dist-info/WHEEL
sixfeetup.customfolderalert-1.3.dist-info/entry_points.txt
sixfeetup.customfolderalert-1.3.dist-info/metadata.json
sixfeetup.customfolderalert-1.3.dist-info/namespace_packages.txt
sixfeetup.customfolderalert-1.3.dist-info/top_level.txt
