Metadata-Version: 2.0
Name: sixfeetup.customfolderalert
Version: 1.3
Summary: Is there evil in your site? This product will let you know.
Home-page: http://www.sixfeetup.com
Author: Six Feet Up, Inc.
Author-email: info@sixfeetup.com
License: GPL
Platform: UNKNOWN
Classifier: Framework :: Plone
Classifier: Programming Language :: Python
Requires-Dist: setuptools
